chorut/__init__.py
chorut/__main__.py
chorut-0.1.4.dist-info/METADATA
chorut-0.1.4.dist-info/WHEEL
chorut-0.1.4.dist-info/entry_points.txt
chorut-0.1.4.dist-info/licenses/LICENSE
chorut-0.1.4.dist-info/RECORD
