Metadata-Version: 2.4
Name: chorut
Version: 0.1.4
Summary: Python implementation of an enhanced chroot functionality with minimal dependencies
Project-URL: Homepage, https://github.com/abuss/chorut
Project-URL: Repository, https://github.com/abuss/chorut.git
Project-URL: Issues, https://github.com/abuss/chorut/issues
Project-URL: Documentation, https://github.com/abuss/chorut#readme
Author: Antal Buss
License: MIT
License-File: LICENSE
Keywords: chroot,containers,linux,namespaces
Classifier: Development Status :: 4 - Beta
Classifier: Environment :: Console
Classifier: Intended Audience :: Developers
Classifier: Intended Audience :: System Administrators
Classifier: License :: OSI Approved :: MIT License
Classifier: Operating System :: POSIX :: Linux
Classifier: Programming Language :: Python :: 3
Classifier: Programming Language :: Python :: 3.12
Classifier: Programming Language :: Python :: 3.13
Classifier: Topic :: Software Development :: Libraries :: Python Modules
Classifier: Topic :: System :: Operating System
Classifier: Topic :: System :: Systems Administration
Classifier: Topic :: Utilities
Requires-Python: >=3.12
Provides-Extra: dev
Requires-Dist: pre-commit>=4.3.0; extra == 'dev'
Requires-Dist: pytest-cov>=4.0; extra == 'dev'
Requires-Dist: pytest>=7.0; extra == 'dev'
Requires-Dist: ruff>=0.1.0; extra == 'dev'
